ragcar/__init__.py
ragcar/ragcar.py
ragcar/models/__init__.py
ragcar/models/base.py
ragcar/models/clova.py
ragcar/models/openai.py
ragcar/tools/__init__.py
ragcar/tools/semantic_search.py
ragcar/tools/semantic_textual_similarity.py
ragcar/tools/sentence_embedding.py
ragcar/tools/text_generation.py
ragcar/tools/text_segmentation.py
ragcar/tools/tokenization.py
ragcar/tools/utils/__init__.py
ragcar/tools/utils/base.py
ragcar/tools/utils/model_config.py
ragcar/utils/__init__.py
ragcar/utils/chat_summarizer.py
ragcar/utils/history_manager.py
ragcar/utils/memory_manager.py
ragcar/utils/prompt_template.py
ragcar/utils/token_limiter.py
ragcar/utils/vector_indexer.py
ragcar-0.1.4.dist-info/LICENSE
ragcar-0.1.4.dist-info/METADATA
ragcar-0.1.4.dist-info/WHEEL
ragcar-0.1.4.dist-info/top_level.txt
ragcar-0.1.4.dist-info/RECORD
